package org.realityforge.fade;

public class Instruction {
  private static final Instruction[] INSTRUCTIONS = new Instruction[256];

  public static final Instruction NOP = new Instruction("NOP", 0, 1);
  public static final Instruction ACONST_NULL = new Instruction("ACONST_NULL", 1, 1);
  public static final Instruction ICONST_M1 = new Instruction("ICONST_M1", 2, 1);
  public static final Instruction ICONST_0 = new Instruction("ICONST_0", 3, 1);
  public static final Instruction ICONST_1 = new Instruction("ICONST_1", 4, 1);
  public static final Instruction ICONST_2 = new Instruction("ICONST_2", 5, 1);
  public static final Instruction ICONST_3 = new Instruction("ICONST_3", 6, 1);
  public static final Instruction ICONST_4 = new Instruction("ICONST_4", 7, 1);
  public static final Instruction ICONST_5 = new Instruction("ICONST_5", 8, 1);
  public static final Instruction LCONST_0 = new Instruction("LCONST_0", 9, 1);
  public static final Instruction LCONST_1 = new Instruction("LCONST_1", 10, 1);
  public static final Instruction FCONST_0 = new Instruction("FCONST_0", 11, 1);
  public static final Instruction FCONST_1 = new Instruction("FCONST_1", 12, 1);
  public static final Instruction FCONST_2 = new Instruction("FCONST_2", 13, 1);
  public static final Instruction DCONST_0 = new Instruction("DCONST_0", 14, 1);
  public static final Instruction DCONST_1 = new Instruction("DCONST_1", 15, 1);
  public static final Instruction BIPUSH = new Instruction("BIPUSH", 16, 2);
  public static final Instruction SIPUSH = new Instruction("SIPUSH", 17, 3);
  public static final Instruction LDC = new Instruction("LDC", 18, 2);
  public static final Instruction LDC_W = new Instruction("LDC_W", 19, 3);
  public static final Instruction LDC2_W = new Instruction("LDC2_W", 20, 3);
  public static final Instruction ILOAD = new Instruction("ILOAD", 21, 2);
  public static final Instruction LLOAD = new Instruction("LLOAD", 22, 2);
  public static final Instruction FLOAD = new Instruction("FLOAD", 23, 2);
  public static final Instruction DLOAD = new Instruction("DLOAD", 24, 2);
  public static final Instruction ALOAD = new Instruction("ALOAD", 25, 2);
  public static final Instruction ILOAD_0 = new Instruction("ILOAD_0", 26, 1);
  public static final Instruction ILOAD_1 = new Instruction("ILOAD_1", 27, 1);
  public static final Instruction ILOAD_2 = new Instruction("ILOAD_2", 28, 1);
  public static final Instruction ILOAD_3 = new Instruction("ILOAD_3", 29, 1);
  public static final Instruction LLOAD_0 = new Instruction("LLOAD_0", 30, 1);
  public static final Instruction LLOAD_1 = new Instruction("LLOAD_1", 31, 1);
  public static final Instruction LLOAD_2 = new Instruction("LLOAD_2", 32, 1);
  public static final Instruction LLOAD_3 = new Instruction("LLOAD_3", 33, 1);
  public static final Instruction FLOAD_0 = new Instruction("FLOAD_0", 34, 1);
  public static final Instruction FLOAD_1 = new Instruction("FLOAD_1", 35, 1);
  public static final Instruction FLOAD_2 = new Instruction("FLOAD_2", 36, 1);
  public static final Instruction FLOAD_3 = new Instruction("FLOAD_3", 37, 1);
  public static final Instruction DLOAD_0 = new Instruction("DLOAD_0", 38, 1);
  public static final Instruction DLOAD_1 = new Instruction("DLOAD_1", 39, 1);
  public static final Instruction DLOAD_2 = new Instruction("DLOAD_2", 40, 1);
  public static final Instruction DLOAD_3 = new Instruction("DLOAD_3", 41, 1);
  public static final Instruction ALOAD_0 = new Instruction("ALOAD_0", 42, 1);
  public static final Instruction ALOAD_1 = new Instruction("ALOAD_1", 43, 1);
  public static final Instruction ALOAD_2 = new Instruction("ALOAD_2", 44, 1);
  public static final Instruction ALOAD_3 = new Instruction("ALOAD_3", 45, 1);
  public static final Instruction IALOAD = new Instruction("IALOAD", 46, 1);
  public static final Instruction LALOAD = new Instruction("LALOAD", 47, 1);
  public static final Instruction FALOAD = new Instruction("FALOAD", 48, 1);
  public static final Instruction DALOAD = new Instruction("DALOAD", 49, 1);
  public static final Instruction AALOAD = new Instruction("AALOAD", 50, 1);
  public static final Instruction BALOAD = new Instruction("BALOAD", 51, 1);
  public static final Instruction CALOAD = new Instruction("CALOAD", 52, 1);
  public static final Instruction SALOAD = new Instruction("SALOAD", 53, 1);
  public static final Instruction ISTORE = new Instruction("ISTORE", 54, 2);
  public static final Instruction LSTORE = new Instruction("LSTORE", 55, 2);
  public static final Instruction FSTORE = new Instruction("FSTORE", 56, 2);
  public static final Instruction DSTORE = new Instruction("DSTORE", 57, 2);
  public static final Instruction ASTORE = new Instruction("ASTORE", 58, 2);
  public static final Instruction ISTORE_0 = new Instruction("ISTORE_0", 59, 1);
  public static final Instruction ISTORE_1 = new Instruction("ISTORE_1", 60, 1);
  public static final Instruction ISTORE_2 = new Instruction("ISTORE_2", 61, 1);
  public static final Instruction ISTORE_3 = new Instruction("ISTORE_3", 62, 1);
  public static final Instruction LSTORE_0 = new Instruction("LSTORE_0", 63, 1);
  public static final Instruction LSTORE_1 = new Instruction("LSTORE_1", 64, 1);
  public static final Instruction LSTORE_2 = new Instruction("LSTORE_2", 65, 1);
  public static final Instruction LSTORE_3 = new Instruction("LSTORE_3", 66, 1);
  public static final Instruction FSTORE_0 = new Instruction("FSTORE_0", 67, 1);
  public static final Instruction FSTORE_1 = new Instruction("FSTORE_1", 68, 1);
  public static final Instruction FSTORE_2 = new Instruction("FSTORE_2", 69, 1);
  public static final Instruction FSTORE_3 = new Instruction("FSTORE_3", 70, 1);
  public static final Instruction DSTORE_0 = new Instruction("DSTORE_0", 71, 1);
  public static final Instruction DSTORE_1 = new Instruction("DSTORE_1", 72, 1);
  public static final Instruction DSTORE_2 = new Instruction("DSTORE_2", 73, 1);
  public static final Instruction DSTORE_3 = new Instruction("DSTORE_3", 74, 1);
  public static final Instruction ASTORE_0 = new Instruction("ASTORE_0", 75, 1);
  public static final Instruction ASTORE_1 = new Instruction("ASTORE_1", 76, 1);
  public static final Instruction ASTORE_2 = new Instruction("ASTORE_2", 77, 1);
  public static final Instruction ASTORE_3 = new Instruction("ASTORE_3", 78, 1);
  public static final Instruction IASTORE = new Instruction("IASTORE", 79, 1);
  public static final Instruction LASTORE = new Instruction("LASTORE", 80, 1);
  public static final Instruction FASTORE = new Instruction("FASTORE", 81, 1);
  public static final Instruction DASTORE = new Instruction("DASTORE", 82, 1);
  public static final Instruction AASTORE = new Instruction("AASTORE", 83, 1);
  public static final Instruction BASTORE = new Instruction("BASTORE", 84, 1);
  public static final Instruction CASTORE = new Instruction("CASTORE", 85, 1);
  public static final Instruction SASTORE = new Instruction("SASTORE", 86, 1);
  public static final Instruction POP = new Instruction("POP", 87, 1);
  public static final Instruction POP2 = new Instruction("POP2", 88, 1);
  public static final Instruction DUP = new Instruction("DUP", 89, 1);
  public static final Instruction DUP_X1 = new Instruction("DUP_X1", 90, 1);
  public static final Instruction DUP_X2 = new Instruction("DUP_X2", 91, 1);
  public static final Instruction DUP2 = new Instruction("DUP2", 92, 1);
  public static final Instruction DUP2_x1 = new Instruction("DUP2_x1", 93, 1);
  public static final Instruction DUP2_x2 = new Instruction("DUP2_x2", 94, 1);
  public static final Instruction SWAP = new Instruction("SWAP", 95, 1);
  public static final Instruction IADD = new Instruction("IADD", 96, 1);
  public static final Instruction LADD = new Instruction("LADD", 97, 1);
  public static final Instruction FADD = new Instruction("FADD", 98, 1);
  public static final Instruction DADD = new Instruction("DADD", 99, 1);
  public static final Instruction ISUB = new Instruction("ISUB", 100, 1);
  public static final Instruction LSUB = new Instruction("LSUB", 101, 1);
  public static final Instruction FSUB = new Instruction("FSUB", 102, 1);
  public static final Instruction DSUB = new Instruction("DSUB", 103, 1);
  public static final Instruction IMUL = new Instruction("IMUL", 104, 1);
  public static final Instruction LMUL = new Instruction("LMUL", 105, 1);
  public static final Instruction FMUL = new Instruction("FMUL", 106, 1);
  public static final Instruction DMUL = new Instruction("DMUL", 107, 1);
  public static final Instruction IDIV = new Instruction("IDIV", 108, 1);
  public static final Instruction LDIV = new Instruction("LDIV", 109, 1);
  public static final Instruction FDIV = new Instruction("FDIV", 110, 1);
  public static final Instruction DDIV = new Instruction("DDIV", 111, 1);
  public static final Instruction IREM = new Instruction("IREM", 112, 1);
  public static final Instruction LREM = new Instruction("LREM", 113, 1);
  public static final Instruction FREM = new Instruction("FREM", 114, 1);
  public static final Instruction DREM = new Instruction("DREM", 115, 1);
  public static final Instruction INEG = new Instruction("INEG", 116, 1);
  public static final Instruction LNEG = new Instruction("LNEG", 117, 1);
  public static final Instruction FNEG = new Instruction("FNEG", 118, 1);
  public static final Instruction DNEG = new Instruction("DNEG", 119, 1);
  public static final Instruction ISHL = new Instruction("ISHL", 120, 1);
  public static final Instruction LSHL = new Instruction("LSHL", 121, 1);
  public static final Instruction ISHR = new Instruction("ISHR", 122, 1);
  public static final Instruction LSHR = new Instruction("LSHR", 123, 1);
  public static final Instruction IUSHR = new Instruction("IUSHR", 124, 1);
  public static final Instruction LUSHR = new Instruction("LUSHR", 125, 1);
  public static final Instruction IAND = new Instruction("IAND", 126, 1);
  public static final Instruction LAND = new Instruction("LAND", 127, 1);
  public static final Instruction IOR = new Instruction("IOR", 128, 1);
  public static final Instruction LOR = new Instruction("LOR", 129, 1);
  public static final Instruction IXOR = new Instruction("IXOR", 130, 1);
  public static final Instruction LXOR = new Instruction("LXOR", 131, 1);
  public static final Instruction IINC = new Instruction("IINC", 132, 3);
  public static final Instruction I2L = new Instruction("I2L", 133, 1);
  public static final Instruction I2F = new Instruction("I2F", 134, 1);
  public static final Instruction I2D = new Instruction("I2D", 135, 1);
  public static final Instruction L2I = new Instruction("L2I", 136, 1);
  public static final Instruction L2F = new Instruction("L2F", 137, 1);
  public static final Instruction L2D = new Instruction("L2D", 138, 1);
  public static final Instruction F2I = new Instruction("F2I", 139, 1);
  public static final Instruction F2L = new Instruction("F2L", 140, 1);
  public static final Instruction F2D = new Instruction("F2D", 141, 1);
  public static final Instruction D2I = new Instruction("D2I", 142, 1);
  public static final Instruction D2L = new Instruction("D2L", 143, 1);
  public static final Instruction D2F = new Instruction("D2F", 144, 1);
  public static final Instruction INT2BYTE = new Instruction("INT2BYTE", 145, 1);
  public static final Instruction INT2CHAR = new Instruction("INT2CHAR", 146, 1);
  public static final Instruction INT2SHORT = new Instruction("INT2SHORT", 147, 1);
  public static final Instruction LCMP = new Instruction("LCMP", 148, 1);
  public static final Instruction FCMPL = new Instruction("FCMPL", 149, 1);
  public static final Instruction FCMPG = new Instruction("FCMPG", 150, 1);
  public static final Instruction DCMPL = new Instruction("DCMPL", 151, 1);
  public static final Instruction DCMPG = new Instruction("DCMPG", 152, 1);
  public static final Instruction IFEQ = new Instruction("IFEQ", 153, 3);
  public static final Instruction IFNE = new Instruction("IFNE", 154, 3);
  public static final Instruction IFLT = new Instruction("IFLT", 155, 3);
  public static final Instruction IFGE = new Instruction("IFGE", 156, 3);
  public static final Instruction IFGT = new Instruction("IFGT", 157, 3);
  public static final Instruction IFLE = new Instruction("IFLE", 158, 3);
  public static final Instruction IF_ICMPEQ = new Instruction("IF_ICMPEQ", 159, 3);
  public static final Instruction IF_ICMPNE = new Instruction("IF_ICMPNE", 160, 3);
  public static final Instruction IF_ICMPLT = new Instruction("IF_ICMPLT", 161, 3);
  public static final Instruction IF_ICMPGE = new Instruction("IF_ICMPGE", 162, 3);
  public static final Instruction IF_ICMPGT = new Instruction("IF_ICMPGT", 163, 3);
  public static final Instruction IF_ICMPLE = new Instruction("IF_ICMPLE", 164, 3);
  public static final Instruction ID_ACMPEQ = new Instruction("ID_ACMPEQ", 165, 3);
  public static final Instruction ID_ACMPNE = new Instruction("ID_ACMPNE", 166, 3);
  public static final Instruction B_GOTO = new Instruction("B_GOTO", 167, 3);
  public static final Instruction JSR = new Instruction("JSR", 168, 3);
  public static final Instruction RET = new Instruction("RET", 169, 2);
  public static final Instruction TABLESWITCH = new Instruction("TABLESWITCH", 170, -1);
  public static final Instruction LOOKUPSWITCH = new Instruction("LOOKUPSWITCH", 171, -1);
  public static final Instruction IRETURN = new Instruction("IRETURN", 172, 1);
  public static final Instruction LRETURN = new Instruction("LRETURN", 173, 1);
  public static final Instruction FRETURN = new Instruction("FRETURN", 174, 1);
  public static final Instruction DRETURN = new Instruction("DRETURN", 175, 1);
  public static final Instruction ARETURN = new Instruction("ARETURN", 176, 1);
  public static final Instruction RETURN = new Instruction("RETURN", 177, 1);
  public static final Instruction GETSTATIC = new Instruction("GETSTATIC", 178, 3);
  public static final Instruction PUTSTATIC = new Instruction("PUTSTATIC", 179, 3);
  public static final Instruction GETFIELD = new Instruction("GETFIELD", 180, 3);
  public static final Instruction PUTFIELD = new Instruction("PUTFIELD", 181, 3);
  public static final Instruction INVOKEVIRTUAL = new Instruction("INVOKEVIRTUAL", 182, 3);
  public static final Instruction INVOKESPECIAL = new Instruction("INVOKESPECIAL", 183, 3);
  public static final Instruction INVOKESTATIC = new Instruction("INVOKESTATIC", 184, 3);
  public static final Instruction INVOKEINTERFACE = new Instruction("INVOKEINTERFACE", 185, 5);
  public static final Instruction UNNUSED1 = new Instruction("UNNUSED1", 186, 0);
  public static final Instruction NEW = new Instruction("NEW", 187, 3);
  public static final Instruction NEWARRAY = new Instruction("NEWARRAY", 188, 2);
  public static final Instruction ANEWARRAY = new Instruction("ANEWARRAY", 189, 3);
  public static final Instruction ARRAYLENGTH = new Instruction("ARRAYLENGTH", 190, 1);
  public static final Instruction ATHROW = new Instruction("ATHROW", 191, 1);
  public static final Instruction CHECKCAST = new Instruction("CHECKCAST", 192, 3);
  public static final Instruction INSTANCEOF = new Instruction("INSTANCEOF", 193, 3);
  public static final Instruction MONITORENTER = new Instruction("MONITORENTER", 194, 1);
  public static final Instruction MONITOREXIT = new Instruction("MONITOREXIT", 195, 1);
  public static final Instruction WIDE = new Instruction("WIDE", 196, -1);
  public static final Instruction MULTIANEWARRAY = new Instruction("MULTIANEWARRAY", 197, 4);
  public static final Instruction IFNULL = new Instruction("IFNULL", 198, 3);
  public static final Instruction IFNONULL = new Instruction("IFNONULL", 199, 3);
  public static final Instruction GOTO_W = new Instruction("GOTO_W", 200, 5);
  public static final Instruction JSR_W = new Instruction("JSR_W", 201, 5);

  public final int code;
  public final int length;
  public final String name;

  public static Instruction fromByteCode(final byte code) {
    return INSTRUCTIONS[code & 0xFF];
  }

  private Instruction(final String name, int code, int length) {
    this.name = name.toLowerCase();
    this.code = code;
    this.length = length;
    INSTRUCTIONS[code] = this;
  }
}
